pysqlx/__init__.py
pysqlx/clients/ClientFactory.py
pysqlx/clients/IClient.py
pysqlx/clients/Pyodbc.py
pysqlx/clients/SqliteThree.py
pysqlx/clients/__init__.py
pysqlx/dialects/IDialect.py
pysqlx/dialects/MsSql.py
pysqlx/dialects/Sqlite.py
pysqlx/dialects/__init__.py
pysqlx/logger/__init__.py
pysqlx/queries/Create.py
pysqlx/queries/Delete.py
pysqlx/queries/Drop.py
pysqlx/queries/GetLength.py
pysqlx/queries/GetTableObject.py
pysqlx/queries/Insert.py
pysqlx/queries/IsEmpty.py
pysqlx/queries/IsExists.py
pysqlx/queries/Query.py
pysqlx/queries/Select.py
pysqlx/queries/SelectDistinct.py
pysqlx/queries/Truncate.py
pysqlx/queries/Union.py
pysqlx/queries/Update.py
pysqlx/queries/__init__.py
pysqlx/queries/utility.py
pysqlx/structures/Database.py
pysqlx/structures/Schema.py
pysqlx/structures/Structure.py
pysqlx/structures/Table.py
pysqlx/structures/__init__.py
pysqlx/structures/columntypes/CharStringColumn.py
pysqlx/structures/columntypes/Column.py
pysqlx/structures/columntypes/DatetimeColumn.py
pysqlx/structures/columntypes/FloatColumn.py
pysqlx/structures/columntypes/IntegerColumn.py
pysqlx/structures/columntypes/TextColumn.py
pysqlx/structures/columntypes/__init__.py
pysqlx/structures/columntypes/logicalclause/And.py
pysqlx/structures/columntypes/logicalclause/Between.py
pysqlx/structures/columntypes/logicalclause/Clause.py
pysqlx/structures/columntypes/logicalclause/Equal.py
pysqlx/structures/columntypes/logicalclause/GreaterThan.py
pysqlx/structures/columntypes/logicalclause/GreaterThanEqual.py
pysqlx/structures/columntypes/logicalclause/InList.py
pysqlx/structures/columntypes/logicalclause/IsNotNull.py
pysqlx/structures/columntypes/logicalclause/IsNull.py
pysqlx/structures/columntypes/logicalclause/LessThan.py
pysqlx/structures/columntypes/logicalclause/LessThanEqual.py
pysqlx/structures/columntypes/logicalclause/Like.py
pysqlx/structures/columntypes/logicalclause/NotBetween.py
pysqlx/structures/columntypes/logicalclause/NotEqual.py
pysqlx-1.0.2.dist-info/LICENSE
pysqlx-1.0.2.dist-info/METADATA
pysqlx-1.0.2.dist-info/WHEEL
pysqlx-1.0.2.dist-info/top_level.txt
pysqlx-1.0.2.dist-info/RECORD
