Metadata-Version: 2.1
Name: pysqlx
Version: 1.0.2
Summary: A simple SQL driver
Home-page: https://github.com/pysqlx/pysqlx
Author: Bassem Girgis
Author-email: brgirgis@gmail.com
Maintainer: Bassem Girgis
Maintainer-email: brgirgis@gmail.com
License: MIT
Download-URL: https://pypi.org/project/pysqlx/
Keywords: sql,database
Platform: UNKNOWN
Classifier: Development Status :: 5 - Production/Stable
Classifier: Intended Audience :: Developers
Classifier: Topic :: Database
Classifier: License :: OSI Approved :: MIT License
Classifier: Programming Language :: Python :: 3.7
Classifier: Programming Language :: Python :: 3.8
Classifier: Programming Language :: Python :: 3.9
Classifier: Programming Language :: Python :: 3.10
License-File: LICENSE
Requires-Dist: pyodbc
